README.rst
setup.cfg
setup.py
dj/__init__.py
dj.subcommand.egg-info/PKG-INFO
dj.subcommand.egg-info/SOURCES.txt
dj.subcommand.egg-info/dependency_links.txt
dj.subcommand.egg-info/namespace_packages.txt
dj.subcommand.egg-info/requires.txt
dj.subcommand.egg-info/top_level.txt
dj/subcommand/__init__.py
dj/subcommand/subcommands.py