Metadata-Version: 1.1
Name: dj.subcommand
Version: 0.0.3
Summary: Django subcommand
Home-page: https://github.com/phlax/dj.subcommand
Author: Ryan Northey
Author-email: ryan@synca.io
License: GPL3
Keywords: django subcommand
Platform: UNKNOWN
Classifier: Development Status :: 4 - Beta
Classifier: Intended Audience :: Developers
Classifier: Topic :: Software Development :: Build Tools
Classifier: License :: OSI Approved :: GNU General Public License v3 or later (GPLv3+)
Classifier: Programming Language :: Python :: 2.7
